dr_widget/__init__.py
dr_widget/py.typed
dr_widget/widgets/__init__.py
dr_widget/widgets/config_file_manager/.gitignore
dr_widget/widgets/config_file_manager/.vscode/extensions.json
dr_widget/widgets/config_file_manager/README.md
dr_widget/widgets/config_file_manager/__init__.py
dr_widget/widgets/config_file_manager/components.json
dr_widget/widgets/config_file_manager/index.html
dr_widget/widgets/config_file_manager/jsrepo.json
dr_widget/widgets/config_file_manager/package.json
dr_widget/widgets/config_file_manager/postcss.config.js
dr_widget/widgets/config_file_manager/public/fonts/Inter-roman.var.woff2
dr_widget/widgets/config_file_manager/public/vite.svg
dr_widget/widgets/config_file_manager/src/App.svelte
dr_widget/widgets/config_file_manager/src/ConfigFileManager.svelte
dr_widget/widgets/config_file_manager/src/app.css
dr_widget/widgets/config_file_manager/src/index.js
dr_widget/widgets/config_file_manager/src/lib/@test_state.json
dr_widget/widgets/config_file_manager/src/lib/Counter.svelte
dr_widget/widgets/config_file_manager/src/lib/components/file-drop/BrowseConfigsPanel.svelte
dr_widget/widgets/config_file_manager/src/lib/components/file-drop/ComplexJsonViewer.svelte
dr_widget/widgets/config_file_manager/src/lib/components/file-drop/ConfigViewerPanel.svelte
dr_widget/widgets/config_file_manager/src/lib/components/file-drop/LoadedConfigPreview.svelte
dr_widget/widgets/config_file_manager/src/lib/components/file-drop/SaveConfigPanel.svelte
dr_widget/widgets/config_file_manager/src/lib/components/file-drop/SelectedFileRow.svelte
dr_widget/widgets/config_file_manager/src/lib/components/file-drop/SelectedFilesList.svelte
dr_widget/widgets/config_file_manager/src/lib/components/file-drop/SimpleJsonViewer.svelte
dr_widget/widgets/config_file_manager/src/lib/components/ui/badge/badge.svelte
dr_widget/widgets/config_file_manager/src/lib/components/ui/badge/index.ts
dr_widget/widgets/config_file_manager/src/lib/components/ui/button/button.svelte
dr_widget-0.1.3.dist-info/WHEEL
dr_widget-0.1.3.dist-info/METADATA
dr_widget-0.1.3.dist-info/RECORD
