Metadata-Version: 2.3
Name: dr-widget
Version: 0.1.3
Summary: Widgets to use with marimo notebooks
Author: Danielle Rothermel
Author-email: Danielle Rothermel <danielle.rothermel@gmail.com>
Requires-Dist: anywidget>=0.9.18
Requires-Dist: marimo==0.17.7
Requires-Dist: pydantic>=2.12.4
Requires-Dist: traitlets>=5.14.3
Requires-Python: >=3.11
